LICENSE
README.md
savestate/__init__.py
savestate/py.typed
savestate/savestate.py
savestate-0.1.2.dist-info/LICENSE
savestate-0.1.2.dist-info/METADATA
savestate-0.1.2.dist-info/WHEEL
savestate-0.1.2.dist-info/RECORD
