Metadata-Version: 2.1
Name: savestate
Version: 0.1.2
Summary: Persistent storage of arbitrary python objects
Home-page: https://mrthearman.github.io/savestate/
License: MIT
Keywords: savestate
Author: Matti Lamppu
Author-email: lamppu.matti.akseli@gmail.com
Requires-Python: >=3.9,<4
Classifier: Intended Audience :: Developers
Classifier: License :: OSI Approved :: MIT License
Classifier: Natural Language :: English
Classifier: Operating System :: OS Independent
Classifier: Programming Language :: Python
Classifier: Programming Language :: Python :: 3
Classifier: Programming Language :: Python :: 3.9
Classifier: Programming Language :: Python :: 3.10
Classifier: Programming Language :: Python :: 3.11
Classifier: Programming Language :: Python :: 3.12
Classifier: Programming Language :: Python :: 3 :: Only
Project-URL: Bug Tracker, https://github.com/MrThearMan/savestate/issues
Project-URL: Repository, https://github.com/MrThearMan/savestate
